dashboard_engine/__init__.py
dashboard_engine-0.0.1.dist-info/LICENSE
dashboard_engine-0.0.1.dist-info/METADATA
dashboard_engine-0.0.1.dist-info/WHEEL
dashboard_engine-0.0.1.dist-info/top_level.txt
dashboard_engine-0.0.1.dist-info/RECORD
