Metadata-Version: 2.1
Name: dashboard-engine
Version: 0.0.1
Summary: A Public stub for dashboard-engine by Plotly
Home-page: https://plotly.com/dash/
Author: Alex Johnson
Author-email: alex@plotly.com
License: Commercial
Platform: UNKNOWN
Classifier: Programming Language :: Python :: 3
Classifier: Framework :: Dash
